MANIFEST.in
README.md
downloads.tar.gz.gpg
extract_music.py
pyproject.toml
music_playlist.egg-info/PKG-INFO
music_playlist.egg-info/SOURCES.txt
music_playlist.egg-info/dependency_links.txt
music_playlist.egg-info/top_level.txt