Metadata-Version: 2.4
Name: music-playlist
Version: 0.15.0
Summary: Music for the masses
Requires-Python: >=3.9
